pyqualitor/__init__.py
pyQualitor-0.0.2.dist-info/METADATA
pyQualitor-0.0.2.dist-info/WHEEL
pyQualitor-0.0.2.dist-info/top_level.txt
pyQualitor-0.0.2.dist-info/RECORD
